{
  "schema_version": "1.1",
  "risk_levels": ["low", "caution", "high"],
  "risk_rank": {
    "low": 0,
    "caution": 1,
    "high": 2
  },
  "scoring_method": [
    "Start from ingredient.base_risk.",
    "Apply profile-based escalation rules using ingredient.tags.",
    "Never lower risk; only escalate.",
    "Final risk is the highest level triggered.",
    "When a profile rule matches, return personalized reason templates where available.",
    "An explicit Avoid List match can be treated as a higher-concern personalized result for that user."
  ],
  "profile_rules": {
    "sensitive": {
      "to_caution_if_tags": [
        "surfactant",
        "ph_adjuster",
        "potential_sting",
        "strong_ph_adjuster",
        "fragrance",
        "sensitive_skin_trigger"
      ],
      "to_high_if_tags": [
        "sensitizer_flag",
        "aha",
        "bha",
        "exfoliant",
        "active"
      ],
      "reason_templates": {
        "surfactant": "Because you have sensitive skin, cleansing agents may feel drying or irritating for you.",
        "ph_adjuster": "Because you have sensitive skin, pH-adjusting ingredients may sting depending on the formula.",
        "potential_sting": "Because you have sensitive skin, this ingredient may increase the chance of stinging.",
        "strong_ph_adjuster": "Because you have sensitive skin, stronger pH-adjusting ingredients deserve extra caution.",
        "fragrance": "Because you have sensitive skin, fragrance may increase the chance of irritation for you.",
        "sensitive_skin_trigger": "Because you have sensitive skin, this ingredient may be less well tolerated for you.",
        "sensitizer_flag": "Because you have sensitive skin, ingredients with sensitization concern deserve extra caution.",
        "aha": "Because you have sensitive skin, AHA exfoliants may be too strong for you.",
        "bha": "Because you have sensitive skin, BHA exfoliants may be too strong for you.",
        "exfoliant": "Because you have sensitive skin, exfoliating ingredients may be too harsh for you.",
        "active": "Because you have sensitive skin, stronger active ingredients may cause stinging or redness."
      }
    },
    "very_sensitive": {
      "to_high_if_tags": [
        "surfactant",
        "ph_adjuster",
        "potential_sting",
        "strong_ph_adjuster",
        "fragrance",
        "sensitive_skin_trigger",
        "sensitizer_flag",
        "aha",
        "bha",
        "exfoliant",
        "active"
      ],
      "reason_templates": {
        "surfactant": "Because your profile says very sensitive skin, cleansing agents deserve extra caution for you.",
        "ph_adjuster": "Because your profile says very sensitive skin, pH-adjusting ingredients deserve extra caution for you.",
        "potential_sting": "Because your profile says very sensitive skin, this ingredient may sting more easily for you.",
        "strong_ph_adjuster": "Because your profile says very sensitive skin, stronger pH-adjusting ingredients deserve extra caution.",
        "fragrance": "Because your profile says very sensitive skin, fragrance may be especially irritating for you.",
        "sensitive_skin_trigger": "Because your profile says very sensitive skin, this ingredient may be a poor fit for you.",
        "sensitizer_flag": "Because your profile says very sensitive skin, sensitizing ingredients deserve extra caution.",
        "aha": "Because your profile says very sensitive skin, AHA exfoliants may be too strong for you.",
        "bha": "Because your profile says very sensitive skin, BHA exfoliants may be too strong for you.",
        "exfoliant": "Because your profile says very sensitive skin, exfoliating ingredients may be too harsh for you.",
        "active": "Because your profile says very sensitive skin, stronger active ingredients may be too harsh for you."
      }
    },
    "eczema": {
      "to_high_if_tags": [
        "aha",
        "bha",
        "exfoliant",
        "active",
        "sensitizer_flag",
        "eczema_trigger"
      ],
      "to_caution_if_tags": [
        "surfactant",
        "potential_sting",
        "strong_ph_adjuster",
        "drying",
        "fragrance"
      ],
      "reason_templates": {
        "aha": "Because you have eczema, AHA exfoliants may irritate your skin barrier.",
        "bha": "Because you have eczema, BHA exfoliants may irritate your skin barrier.",
        "exfoliant": "Because you have eczema, exfoliating ingredients may be too harsh for your skin barrier.",
        "active": "Because you have eczema, stronger active ingredients may be irritating for you.",
        "sensitizer_flag": "Because you have eczema, ingredients with sensitization concern deserve extra caution.",
        "eczema_trigger": "Because you have eczema, this ingredient may be less comfortable for your skin barrier.",
        "surfactant": "Because you have eczema, cleansing agents may strip or dry your skin barrier.",
        "potential_sting": "Because you have eczema, this ingredient may sting on compromised skin.",
        "strong_ph_adjuster": "Because you have eczema, stronger pH-adjusting ingredients deserve extra caution.",
        "drying": "Because you have eczema, drying ingredients may worsen skin discomfort.",
        "fragrance": "Because you have eczema, fragrance may increase the chance of irritation."
      }
    },
    "rosacea": {
      "to_high_if_tags": [
        "aha",
        "bha",
        "exfoliant",
        "active",
        "sensitizer_flag",
        "rosacea_trigger"
      ],
      "to_caution_if_tags": [
        "surfactant",
        "potential_sting",
        "strong_ph_adjuster",
        "fragrance"
      ],
      "reason_templates": {
        "aha": "Because you have rosacea, AHA exfoliants may increase redness or irritation.",
        "bha": "Because you have rosacea, BHA exfoliants may increase irritation for you.",
        "exfoliant": "Because you have rosacea, exfoliating ingredients may be too harsh for your skin.",
        "active": "Because you have rosacea, stronger active ingredients may trigger discomfort.",
        "sensitizer_flag": "Because you have rosacea, sensitizing ingredients deserve extra caution.",
        "rosacea_trigger": "Because you have rosacea, this ingredient may be less comfortable for your skin.",
        "surfactant": "Because you have rosacea, stronger cleansing agents may feel irritating.",
        "potential_sting": "Because you have rosacea, this ingredient may increase the chance of stinging.",
        "strong_ph_adjuster": "Because you have rosacea, strong pH-adjusting ingredients deserve extra caution.",
        "fragrance": "Because you have rosacea, fragrance may increase the chance of irritation."
      }
    },
    "psoriasis": {
      "to_high_if_tags": [
        "aha",
        "bha",
        "exfoliant",
        "active",
        "sensitizer_flag",
        "psoriasis_trigger"
      ],
      "to_caution_if_tags": [
        "surfactant",
        "potential_sting",
        "strong_ph_adjuster",
        "drying",
        "fragrance"
      ],
      "reason_templates": {
        "aha": "Because you have psoriasis, AHA exfoliants may feel too strong for your skin.",
        "bha": "Because you have psoriasis, BHA exfoliants may feel too strong for your skin.",
        "exfoliant": "Because you have psoriasis, exfoliating ingredients may be too harsh for your skin.",
        "active": "Because you have psoriasis, stronger active ingredients may increase discomfort.",
        "sensitizer_flag": "Because you have psoriasis, sensitizing ingredients deserve extra caution.",
        "psoriasis_trigger": "Because you have psoriasis, this ingredient may be less comfortable for your skin.",
        "surfactant": "Because you have psoriasis, stronger cleansing agents may feel drying.",
        "potential_sting": "Because you have psoriasis, this ingredient may increase the chance of stinging.",
        "strong_ph_adjuster": "Because you have psoriasis, stronger pH-adjusting ingredients deserve extra caution.",
        "drying": "Because you have psoriasis, drying ingredients may worsen discomfort.",
        "fragrance": "Because you have psoriasis, fragrance may increase the chance of irritation."
      }
    },
    "fragrance": {
      "to_high_if_tags": ["fragrance"],
      "to_caution_if_tags": ["sensitizer_flag"],
      "reason_templates": {
        "fragrance": "Because you marked fragrance sensitivity, fragranced ingredients may not be a good fit for you.",
        "sensitizer_flag": "Because you marked fragrance sensitivity, sensitizing ingredients deserve extra caution."
      }
    },
    "parabens": {
      "to_caution_if_tags": ["paraben"],
      "reason_templates": {
        "paraben": "Because you chose to avoid parabens, this ingredient matches that preference."
      }
    },
    "sulfates": {
      "to_caution_if_tags": ["sulfate"],
      "reason_templates": {
        "sulfate": "Because you chose to avoid sulfates, this ingredient matches that preference."
      }
    }
  },
  "ingredient_id_overrides": {
    "methylisothiazolinone": {
      "always_at_least": "high",
      "reason": "Ingredient has tags: sensitizer_flag/high_attention."
    }
  },
  "output_fields": {
    "include_triggered_profile_rules": true,
    "include_matched_tags": true,
    "include_risk_notes": true,
    "include_personal_reasons": true,
    "include_personalized_watchouts": true
  }
}